smirk-0.2.0.dist-info/METADATA
smirk-0.2.0.dist-info/WHEEL
smirk-0.2.0.dist-info/licenses/LICENSE
smirk/vocab_smiles.json
smirk/cli.py
smirk/vocab_selfies.json
smirk/__init__.py
smirk/smirk.cpython-313-i386-linux-gnu.so
smirk-0.2.0.dist-info/RECORD
