Metadata-Version: 2.4
Name: smirk
Version: 0.2.0
Classifier: Programming Language :: Rust
Classifier: Programming Language :: Python :: Implementation :: CPython
Classifier: Programming Language :: Python :: Implementation :: PyPy
Requires-Dist: transformers >=4.40, <5
License-File: LICENSE
Summary: A chemically complete tokenizer for OpenSMILES
Home-Page: https://eeg.engin.umich.edu/smirk
Author: Anoushka Bhutani
Author-email: Alexius Wadell <awadell@umich.edu>
License: Apache-2.0
Requires-Python: >=3.9
Project-URL: source, https://github.com/BattModels/smirk
Project-URL: homepage, https://eeg.engin.umich.edu/smirk
Project-URL: documentation, https://eeg.engin.umich.edu/smirk
Project-URL: issues, https://github.com/BattModels/smirk/issues
Project-URL: changelog, https://github.com/BattModels/smirk/blob/main/CHANGELOG.md
